epicarousel/__init__.py
epicarousel/construction.sh
epicarousel/core.py
epicarousel/evaluate.py
epicarousel/identify_metacells.py
epicarousel/preprocess.py
epicarousel/version.py
epicarousel-0.0.8.dist-info/LICENSE
epicarousel-0.0.8.dist-info/METADATA
epicarousel-0.0.8.dist-info/WHEEL
epicarousel-0.0.8.dist-info/top_level.txt
epicarousel-0.0.8.dist-info/RECORD
