Metadata-Version: 2.1
Name: epicarousel
Version: 0.0.8
Summary: EpiCarousel: memory- and time-efficient identification of metacells for atlas-level single-cell chromatin accessibility data
Home-page: https://github.com/BioX-NKU/EpiCarousel
Author: Shengquan Chen, Sijie Li and Yuxi Li
License: MIT Licence
Keywords: pip,epicarousel
Classifier: Intended Audience :: Science/Research
Classifier: License :: OSI Approved :: MIT License
Classifier: Programming Language :: Python :: 3.10
Classifier: Operating System :: MacOS :: MacOS X
Classifier: Operating System :: Microsoft :: Windows
Classifier: Operating System :: POSIX :: Linux
Classifier: Topic :: Scientific/Engineering :: Bio-Informatics
Requires-Python: >=3.10.0
License-File: LICENSE
Requires-Dist: scanpy >=1.8.2
Requires-Dist: anndata >=0.8.0
Requires-Dist: snapatac2 >=2.3.1
Requires-Dist: episcanpy >=0.3.2
Requires-Dist: numpy >=1.26.2
Requires-Dist: pandas >=1.5.3
Requires-Dist: seaborn
Requires-Dist: igraph
Requires-Dist: leidenalg
Requires-Dist: louvain
Requires-Dist: shutilwhich
Requires-Dist: memory-profiler
Requires-Dist: scipy
Requires-Dist: tqdm
